{
  "ticket_id": "OMN-12299",
  "run_timestamp": "2026-05-28T20:50:30.000000+00:00",
  "status": "PASS",
  "summary": "PR merged \u2014 OmniNode-ai/omnimarket#938 merged to main on 2026-05-28",
  "checks": [
    {
      "evidence_id": "dod-001",
      "description": "PR #938 (omnimarket) merged to main",
      "status": "PASS",
      "message": "PR OmniNode-ai/omnimarket#938 'feat(OMN-12245): add node_ledger_stats_compute pure compute node' merged 2026-05-28T15:21:49Z"
    },
    {
      "evidence_id": "dod-002",
      "description": "Backfill triage closeout \u2014 ticket created in Backlog for completed work",
      "status": "PASS",
      "message": "Evidence created during batch triage closeout on 2026-05-28"
    }
  ]
}