{
  "ticket_id": "OMN-12138",
  "run_timestamp": "2026-05-26T12:08:19.053239+00:00",
  "status": "PASS",
  "summary": "PR merged \u2014 OmniNode-ai/omnidash#126 merged to main on 2026-05-25",
  "checks": [
    {
      "evidence_id": "dod-001",
      "description": "PR #126 (omnidash) merged to main",
      "status": "PASS",
      "message": "PR OmniNode-ai/omnidash#126 merged to main on 2026-05-25"
    },
    {
      "evidence_id": "dod-002",
      "description": "Triage evidence backfill \u2014 ticket has merged PR but was missing OCC evidence",
      "status": "PASS",
      "message": "Evidence created during batch triage closeout on 2026-05-26"
    }
  ]
}
